tinyfan/__init__.py
tinyfan/argo_typing.py
tinyfan/cli.py
tinyfan/codegen.py
tinyfan/config.py
tinyfan/dagviz.py
tinyfan/flow.py
tinyfan/flowrundata.py
tinyfan/py.typed
tinyfan/resources/__init__.py
tinyfan/resources/base.py
tinyfan/stores/__init__.py
tinyfan/stores/base.py
tinyfan/stores/bigquery.py
tinyfan/stores/gcs_pickle.py
tinyfan/stores/naive.py
tinyfan/utils/__init__.py
tinyfan/utils/embed.py
tinyfan/utils/exjson.py
tinyfan/utils/merge.py
tinyfan/utils/typing.py
tinyfan/utils/yaml.py
tinyfan-0.2.8.dist-info/METADATA
tinyfan-0.2.8.dist-info/WHEEL
tinyfan-0.2.8.dist-info/entry_points.txt
tinyfan-0.2.8.dist-info/RECORD
