Metadata-Version: 2.4
Name: tinyfan
Version: 0.2.8
Summary: Tiny Argo Workflows python devkit
Project-URL: Documentation, https://github.com/eunchuldev/tinyfan#readme
Project-URL: Issues, https://github.com/eunchuldev/tinyfan/issues
Project-URL: Source, https://github.com/eunchuldev/tinyfan
Author-email: eunchuldev <eunchulsong@gmail.com>
Keywords: argo-workflow,pipeline,tinyfan,workflow
Classifier: License :: OSI Approved :: MIT License
Classifier: Operating System :: OS Independent
Classifier: Programming Language :: Python :: 3.10
Classifier: Programming Language :: Python :: 3.11
Classifier: Programming Language :: Python :: 3.12
Classifier: Typing :: Typed
Requires-Python: >=3.12
Requires-Dist: croniter>=3.0.3
Requires-Dist: pyyaml>=6.0.2
Requires-Dist: typer-slim>=0.15.1
Provides-Extra: all
Requires-Dist: google-cloud-bigquery[pandas]; extra == 'all'
Requires-Dist: google-cloud-storage; extra == 'all'
Requires-Dist: networkx; extra == 'all'
Requires-Dist: pandas; extra == 'all'
Requires-Dist: pyarrow; extra == 'all'
Provides-Extra: bigquery
Requires-Dist: google-cloud-bigquery[pandas]; extra == 'bigquery'
Requires-Dist: pandas; extra == 'bigquery'
Requires-Dist: pyarrow; extra == 'bigquery'
Provides-Extra: dev
Requires-Dist: google-cloud-bigquery[pandas]; extra == 'dev'
Requires-Dist: google-cloud-storage; extra == 'dev'
Requires-Dist: jsonpatch>=1; extra == 'dev'
Requires-Dist: jsonschema[format]; extra == 'dev'
Requires-Dist: mypy>=1.14; extra == 'dev'
Requires-Dist: networkx; extra == 'dev'
Requires-Dist: pandas; extra == 'dev'
Requires-Dist: pyarrow; extra == 'dev'
Requires-Dist: pytest>=8.3.3; extra == 'dev'
Requires-Dist: ruff; extra == 'dev'
Requires-Dist: types-croniter; extra == 'dev'
Requires-Dist: types-jsonschema; extra == 'dev'
Requires-Dist: types-pyyaml; extra == 'dev'
Provides-Extra: gcs
Requires-Dist: google-cloud-storage; extra == 'gcs'
Provides-Extra: pandas
Requires-Dist: pandas; extra == 'pandas'
Requires-Dist: pyarrow; extra == 'pandas'
Provides-Extra: viz
Requires-Dist: networkx; extra == 'viz'
